setup.py
TheZine.egg-info/PKG-INFO
TheZine.egg-info/SOURCES.txt
TheZine.egg-info/dependency_links.txt
TheZine.egg-info/not-zip-safe
TheZine.egg-info/requires.txt
TheZine.egg-info/top_level.txt
tests/test_article_author.py
tests/test_article_from_link.py
tests/test_author_contacts.py
tests/test_get_articles.py
tests/test_utils.py
tz/__init__.py
tz/constants.py
tz/tz.py
tz/utils.py