Metadata-Version: 1.0
Name: TheZine
Version: 0.0.1
Summary: Python API for The Zine
Home-page: http://github.com/voidabhi/TheZineAPI
Author: Abhijeet Mohan
Author-email: abhijeetshibu@gmail.com
License: MIT
Platform: UNKNOWN
